Metadata-Version: 2.4
Name: nanomonsv
Version: 0.8.1
Summary: Python tools for detecting structural variation from nanopore sequence data
Author-email: Yuichi Shiraishi <friend1ws@gmail.com>
License: GPL-3.0-or-later
Project-URL: Homepage, https://github.com/friend1ws/nanomonsv
Classifier: Development Status :: 4 - Beta
Classifier: Intended Audience :: Science/Research
Classifier: License :: OSI Approved :: GNU General Public License v3 (GPLv3)
Classifier: Operating System :: Unix
Classifier: Programming Language :: Python :: 3.9
Classifier: Programming Language :: Python :: 3.10
Classifier: Programming Language :: Python :: 3.11
Classifier: Programming Language :: Python :: 3.12
Classifier: Topic :: Scientific/Engineering :: Bio-Informatics
Requires-Python: >=3.9
License-File: LICENSE
Requires-Dist: numpy
Requires-Dist: parasail
Requires-Dist: pysam
Requires-Dist: h5py
Dynamic: license-file
